beetsplug/describe/__init__.py
beetsplug/describe/about.py
beetsplug/describe/command.py
beetsplug/describe/common.py
beetsplug/describe/config_default.yml
beets_describe-0.0.5.dist-info/LICENSE.txt
beets_describe-0.0.5.dist-info/METADATA
beets_describe-0.0.5.dist-info/WHEEL
beets_describe-0.0.5.dist-info/top_level.txt
beets_describe-0.0.5.dist-info/RECORD
