Metadata-Version: 2.1
Name: beets-describe
Version: 0.0.5
Summary: ('A beets plugin that describes attributes in depth',)
Home-page: https://github.com/adamjakab/BeetsPluginDescribe
Author: Adam Jakab
Author-email: adam@jakab.pro
License: MIT
Platform: ALL
Classifier: Topic :: Multimedia :: Sound/Audio
Classifier: License :: OSI Approved :: MIT License
Classifier: Environment :: Console
Classifier: Programming Language :: Python :: 3
Classifier: Programming Language :: Python :: 3.8
Classifier: Programming Language :: Python :: 3.9
Classifier: Programming Language :: Python :: 3.10
Classifier: Programming Language :: Python :: 3.11
Classifier: Programming Language :: Python :: 3.12
Requires-Python: >=3.8
License-File: LICENSE.txt
Requires-Dist: beets >=1.4.9
Requires-Dist: numpy
Requires-Dist: pandas
Requires-Dist: termtables
Requires-Dist: termplotlib
Provides-Extra: tests
